LICENSE.txt
MANIFEST.in
README.rst
setup.cfg
setup.py
docs/_build/html/_sources/Code.txt
docs/_build/html/_sources/README.txt
docs/_build/html/_sources/index.txt
pydatasentry/__init__.py
pydatasentry/attributes.py
pydatasentry/capture.py
pydatasentry/config.py
pydatasentry/helpers.py
pydatasentry/instrumentation.py
pydatasentry/lineage.py
pydatasentry/process.py
pydatasentry/signature.py
pydatasentry.egg-info/PKG-INFO
pydatasentry.egg-info/SOURCES.txt
pydatasentry.egg-info/dependency_links.txt
pydatasentry.egg-info/top_level.txt