Metadata-Version: 1.1
Name: pydatasentry
Version: 0.1.4
Summary: Memory tool for Python-Based Data Science
Home-page: http://github.com/FourthLion/pydatasentry
Author: Venkata Pingali
Author-email: pingali@gmail.com
License: MIT
Download-URL: https://github.com/FourthLion/pydatasentry/tarball/0.1.4
Keywords: pydata,pandas,documentation,regressions,tool
Platform: UNKNOWN
Classifier: Development Status :: 3 - Alpha
Classifier: License :: OSI Approved :: MIT License
Classifier: Programming Language :: Python :: 3 :: Only
Classifier: Topic :: Scientific/Engineering :: Information Analysis
